{
	"info": {
		"_postman_id": "1683213c-145c-4c76-a5a3-e476da923f90",
		"name": "IP Address Management",
		"schema": "https://schema.getpostman.com/json/collection/v2.1.0/collection.json"
	},
	"item": [
		{
			"name": "Auth",
			"item": [
				{
					"name": "Login",
					"request": {
						"method": "POST",
						"header": [
							{
								"key": "Content-Type",
								"value": "application/json",
								"type": "text"
							},
							{
								"key": "Accept",
								"value": "application/json",
								"type": "text"
							}
						],
						"body": {
							"mode": "raw",
							"raw": "{\n    \"email\": \"satrya@freshcms.net\",\n    \"password\": \"12345678\"\n}"
						},
						"url": {
							"raw": "{{url}}/api/auth/login",
							"host": [
								"{{url}}"
							],
							"path": [
								"api",
								"auth",
								"login"
							]
						}
					},
					"response": []
				},
				{
					"name": "Register",
					"request": {
						"method": "POST",
						"header": [
							{
								"key": "Content-Type",
								"value": "application/json",
								"type": "default"
							},
							{
								"key": "Accept",
								"value": "application/json",
								"type": "default"
							}
						],
						"body": {
							"mode": "raw",
							"raw": "{\n    \"full_name\": \"Satrya\",\n    \"nick_name\": \"Wiguna\",\n    \"email\": \"satrya@freshcms.net\",\n    \"password\": \"12345678\",\n    \"confirm_password\": \"12345678\"\n}"
						},
						"url": {
							"raw": "{{url}}/api/register",
							"host": [
								"{{url}}"
							],
							"path": [
								"api",
								"register"
							]
						}
					},
					"response": []
				},
				{
					"name": "Logout",
					"request": {
						"auth": {
							"type": "bearer",
							"bearer": [
								{
									"key": "token",
									"value": "{{token}}",
									"type": "string"
								}
							]
						},
						"method": "POST",
						"header": [
							{
								"key": "Content-Type",
								"value": "application/json",
								"type": "text"
							},
							{
								"key": "Accept",
								"value": "application/json",
								"type": "text"
							}
						],
						"body": {
							"mode": "raw",
							"raw": "{\n    \"email\": \"satrya@freshcms.net\"\n}"
						},
						"url": {
							"raw": "{{url}}/api/auth/logout",
							"host": [
								"{{url}}"
							],
							"path": [
								"api",
								"auth",
								"logout"
							]
						}
					},
					"response": []
				}
			]
		},
		{
			"name": "IP",
			"item": [
				{
					"name": "Get All",
					"request": {
						"auth": {
							"type": "bearer",
							"bearer": [
								{
									"key": "token",
									"value": "{{token}}",
									"type": "string"
								}
							]
						},
						"method": "GET",
						"header": [
							{
								"key": "Content-Type",
								"value": "application/json",
								"type": "text"
							},
							{
								"key": "Accept",
								"value": "application/json",
								"type": "text"
							}
						],
						"url": {
							"raw": "{{url}}/api/manage/ip",
							"host": [
								"{{url}}"
							],
							"path": [
								"api",
								"manage",
								"ip"
							]
						}
					},
					"response": []
				},
				{
					"name": "Get",
					"protocolProfileBehavior": {
						"disableBodyPruning": true
					},
					"request": {
						"auth": {
							"type": "bearer",
							"bearer": [
								{
									"key": "token",
									"value": "{{token}}",
									"type": "string"
								}
							]
						},
						"method": "GET",
						"header": [
							{
								"key": "Content-Type",
								"value": "application/json",
								"type": "text"
							},
							{
								"key": "Accept",
								"value": "application/json",
								"type": "text"
							}
						],
						"body": {
							"mode": "raw",
							"raw": ""
						},
						"url": {
							"raw": "{{url}}/api/manage/ip/10",
							"host": [
								"{{url}}"
							],
							"path": [
								"api",
								"manage",
								"ip",
								"10"
							]
						}
					},
					"response": []
				},
				{
					"name": "Get Search",
					"request": {
						"auth": {
							"type": "bearer",
							"bearer": [
								{
									"key": "token",
									"value": "{{token}}",
									"type": "string"
								}
							]
						},
						"method": "POST",
						"header": [
							{
								"key": "Content-Type",
								"value": "application/json",
								"type": "text"
							},
							{
								"key": "Accept",
								"value": "application/json",
								"type": "text"
							}
						],
						"body": {
							"mode": "raw",
							"raw": "{\n    \"search\": \"\"\n}",
							"options": {
								"raw": {
									"language": "json"
								}
							}
						},
						"url": {
							"raw": "{{url}}/api/manage/ip/search",
							"host": [
								"{{url}}"
							],
							"path": [
								"api",
								"manage",
								"ip",
								"search"
							]
						}
					},
					"response": []
				},
				{
					"name": "Get Search Page",
					"request": {
						"auth": {
							"type": "bearer",
							"bearer": [
								{
									"key": "token",
									"value": "{{token}}",
									"type": "string"
								}
							]
						},
						"method": "POST",
						"header": [
							{
								"key": "Content-Type",
								"value": "application/json",
								"type": "text"
							},
							{
								"key": "Accept",
								"value": "application/json",
								"type": "text"
							}
						],
						"body": {
							"mode": "raw",
							"raw": "{\n    \"search\": \"\"\n}",
							"options": {
								"raw": {
									"language": "json"
								}
							}
						},
						"url": {
							"raw": "{{url}}/api/manage/ip/search/page/10/0",
							"host": [
								"{{url}}"
							],
							"path": [
								"api",
								"manage",
								"ip",
								"search",
								"page",
								"10",
								"0"
							]
						}
					},
					"response": []
				},
				{
					"name": "Create",
					"request": {
						"auth": {
							"type": "bearer",
							"bearer": [
								{
									"key": "token",
									"value": "{{token}}",
									"type": "string"
								}
							]
						},
						"method": "POST",
						"header": [
							{
								"key": "Content-Type",
								"value": "application/json",
								"type": "text"
							},
							{
								"key": "Accept",
								"value": "application/json",
								"type": "text"
							}
						],
						"body": {
							"mode": "raw",
							"raw": "{\n    \"ipv4\": \"127.0.0.2\",\n    \"label\": [\n        {\n            \"id\": 10,\n            \"title\": \"Comment 1.1\"\n        }\n    ]\n}",
							"options": {
								"raw": {
									"language": "json"
								}
							}
						},
						"url": {
							"raw": "{{url}}/api/manage/ip/",
							"host": [
								"{{url}}"
							],
							"path": [
								"api",
								"manage",
								"ip",
								""
							]
						}
					},
					"response": []
				},
				{
					"name": "Update",
					"request": {
						"auth": {
							"type": "bearer",
							"bearer": [
								{
									"key": "token",
									"value": "{{token}}",
									"type": "string"
								}
							]
						},
						"method": "PUT",
						"header": [
							{
								"key": "Content-Type",
								"value": "application/json",
								"type": "text"
							},
							{
								"key": "Accept",
								"value": "application/json",
								"type": "text"
							}
						],
						"body": {
							"mode": "raw",
							"raw": "{\n    \"label\": [\n        {\n            \"id\": 10,\n            \"title\": \"Comment 1.1\"\n        }\n    ]\n}",
							"options": {
								"raw": {
									"language": "json"
								}
							}
						},
						"url": {
							"raw": "{{url}}/api/manage/ip/10",
							"host": [
								"{{url}}"
							],
							"path": [
								"api",
								"manage",
								"ip",
								"10"
							]
						}
					},
					"response": []
				},
				{
					"name": "Remove",
					"request": {
						"auth": {
							"type": "bearer",
							"bearer": [
								{
									"key": "token",
									"value": "{{token}}",
									"type": "string"
								}
							]
						},
						"method": "DELETE",
						"header": [
							{
								"key": "Content-Type",
								"value": "application/json",
								"type": "text"
							},
							{
								"key": "Accept",
								"value": "application/json",
								"type": "text"
							}
						],
						"body": {
							"mode": "raw",
							"raw": "",
							"options": {
								"raw": {
									"language": "json"
								}
							}
						},
						"url": {
							"raw": "{{url}}/api/manage/ip/10",
							"host": [
								"{{url}}"
							],
							"path": [
								"api",
								"manage",
								"ip",
								"10"
							]
						}
					},
					"response": []
				}
			]
		},
		{
			"name": "Label",
			"item": [
				{
					"name": "Get All",
					"request": {
						"auth": {
							"type": "bearer",
							"bearer": [
								{
									"key": "token",
									"value": "{{token}}",
									"type": "string"
								}
							]
						},
						"method": "GET",
						"header": [
							{
								"key": "Content-Type",
								"value": "application/json",
								"type": "text"
							},
							{
								"key": "Accept",
								"value": "application/json",
								"type": "text"
							}
						],
						"url": {
							"raw": "{{url}}/api/manage/label",
							"host": [
								"{{url}}"
							],
							"path": [
								"api",
								"manage",
								"label"
							]
						}
					},
					"response": []
				},
				{
					"name": "Get",
					"protocolProfileBehavior": {
						"disableBodyPruning": true
					},
					"request": {
						"auth": {
							"type": "bearer",
							"bearer": [
								{
									"key": "token",
									"value": "{{token}}",
									"type": "string"
								}
							]
						},
						"method": "GET",
						"header": [
							{
								"key": "Content-Type",
								"value": "application/json",
								"type": "text"
							},
							{
								"key": "Accept",
								"value": "application/json",
								"type": "text"
							}
						],
						"body": {
							"mode": "raw",
							"raw": ""
						},
						"url": {
							"raw": "{{url}}/api/manage/label/10",
							"host": [
								"{{url}}"
							],
							"path": [
								"api",
								"manage",
								"label",
								"10"
							]
						}
					},
					"response": []
				},
				{
					"name": "Get Search",
					"request": {
						"auth": {
							"type": "bearer",
							"bearer": [
								{
									"key": "token",
									"value": "{{token}}",
									"type": "string"
								}
							]
						},
						"method": "POST",
						"header": [
							{
								"key": "Content-Type",
								"value": "application/json",
								"type": "text"
							},
							{
								"key": "Accept",
								"value": "application/json",
								"type": "text"
							}
						],
						"body": {
							"mode": "raw",
							"raw": "{\n    \"search\": \"\"\n}",
							"options": {
								"raw": {
									"language": "json"
								}
							}
						},
						"url": {
							"raw": "{{url}}/api/manage/label/search",
							"host": [
								"{{url}}"
							],
							"path": [
								"api",
								"manage",
								"label",
								"search"
							]
						}
					},
					"response": []
				},
				{
					"name": "Get Search Page",
					"request": {
						"auth": {
							"type": "bearer",
							"bearer": [
								{
									"key": "token",
									"value": "{{token}}",
									"type": "string"
								}
							]
						},
						"method": "POST",
						"header": [
							{
								"key": "Content-Type",
								"value": "application/json",
								"type": "text"
							},
							{
								"key": "Accept",
								"value": "application/json",
								"type": "text"
							}
						],
						"body": {
							"mode": "raw",
							"raw": "{\n    \"search\": \"\"\n}",
							"options": {
								"raw": {
									"language": "json"
								}
							}
						},
						"url": {
							"raw": "{{url}}/api/manage/label/search/page/10/0",
							"host": [
								"{{url}}"
							],
							"path": [
								"api",
								"manage",
								"label",
								"search",
								"page",
								"10",
								"0"
							]
						}
					},
					"response": []
				},
				{
					"name": "Create",
					"request": {
						"auth": {
							"type": "bearer",
							"bearer": [
								{
									"key": "token",
									"value": "{{token}}",
									"type": "string"
								}
							]
						},
						"method": "POST",
						"header": [
							{
								"key": "Content-Type",
								"value": "application/json",
								"type": "text"
							},
							{
								"key": "Accept",
								"value": "application/json",
								"type": "text"
							}
						],
						"body": {
							"mode": "raw",
							"raw": "{\n    \"title\": \"Title 1\"\n}",
							"options": {
								"raw": {
									"language": "json"
								}
							}
						},
						"url": {
							"raw": "{{url}}/api/manage/label/",
							"host": [
								"{{url}}"
							],
							"path": [
								"api",
								"manage",
								"label",
								""
							]
						}
					},
					"response": []
				},
				{
					"name": "Update",
					"request": {
						"auth": {
							"type": "bearer",
							"bearer": [
								{
									"key": "token",
									"value": "{{token}}",
									"type": "string"
								}
							]
						},
						"method": "PUT",
						"header": [
							{
								"key": "Content-Type",
								"value": "application/json",
								"type": "text"
							},
							{
								"key": "Accept",
								"value": "application/json",
								"type": "text"
							}
						],
						"body": {
							"mode": "raw",
							"raw": "{\n    \"title\": \"Title 1.1\"\n}",
							"options": {
								"raw": {
									"language": "json"
								}
							}
						},
						"url": {
							"raw": "{{url}}/api/manage/label/17",
							"host": [
								"{{url}}"
							],
							"path": [
								"api",
								"manage",
								"label",
								"17"
							]
						}
					},
					"response": []
				},
				{
					"name": "Remove",
					"request": {
						"auth": {
							"type": "bearer",
							"bearer": [
								{
									"key": "token",
									"value": "{{token}}",
									"type": "string"
								}
							]
						},
						"method": "DELETE",
						"header": [
							{
								"key": "Content-Type",
								"value": "application/json",
								"type": "text"
							},
							{
								"key": "Accept",
								"value": "application/json",
								"type": "text"
							}
						],
						"body": {
							"mode": "raw",
							"raw": "",
							"options": {
								"raw": {
									"language": "json"
								}
							}
						},
						"url": {
							"raw": "{{url}}/api/manage/label/17",
							"host": [
								"{{url}}"
							],
							"path": [
								"api",
								"manage",
								"label",
								"17"
							]
						}
					},
					"response": []
				}
			]
		}
	]
}